land.copernicus.content-3.8-py2.7-nspkg.pth
land/copernicus/content/__init__.py
land/copernicus/content/adapter.py
land/copernicus/content/config.py
land/copernicus/content/configure.zcml
land/copernicus/content/globalhandlers.py
land/copernicus/content/overrides.zcml
land/copernicus/content/patches.py
land/copernicus/content/permissions.zcml
land/copernicus/content/profiles.zcml
land/copernicus/content/setuphandlers.py
land/copernicus/content/userdataschema.py
land/copernicus/content/version.txt
land/copernicus/content/async/__init__.py
land/copernicus/content/async/configure.zcml
land/copernicus/content/async/subscribers.py
land/copernicus/content/browser/__init__.py
land/copernicus/content/browser/backports.zcml
land/copernicus/content/browser/configure.zcml
land/copernicus/content/browser/cookiepolicy.zcml
land/copernicus/content/browser/dataservice_backports.py
land/copernicus/content/browser/download.py
land/copernicus/content/browser/forms.py
land/copernicus/content/browser/frozenEntrynoclick.js
land/copernicus/content/browser/landitem.py
land/copernicus/content/browser/landitem.zcml
land/copernicus/content/browser/markFrozen.js
land/copernicus/content/browser/migration.py
land/copernicus/content/browser/patches.zcml
land/copernicus/content/browser/scripts.py
land/copernicus/content/browser/users_statistics.py
land/copernicus/content/browser/viewlets.py
land/copernicus/content/browser/views.py
land/copernicus/content/browser/images/land.png
land/copernicus/content/browser/static/landitem_view.css
land/copernicus/content/browser/static/landitem_view.js
land/copernicus/content/browser/static/lib/jquery.dataTables.min.css
land/copernicus/content/browser/static/lib/jquery.dataTables.min.js
land/copernicus/content/browser/template-overrides/Products.CMFPlone.skins.plone_form_scripts.send_feedback_site.cpy
land/copernicus/content/browser/template-overrides/Products.CMFPlone.skins.plone_login.login_form.cpt
land.copernicus.content-3.8.dist-info/DESCRIPTION.rst
land.copernicus.content-3.8.dist-info/METADATA
land.copernicus.content-3.8.dist-info/RECORD
land.copernicus.content-3.8.dist-info/WHEEL
land.copernicus.content-3.8.dist-info/entry_points.txt
land.copernicus.content-3.8.dist-info/metadata.json
land.copernicus.content-3.8.dist-info/namespace_packages.txt
land.copernicus.content-3.8.dist-info/top_level.txt
