Metadata-Version: 2.0
Name: land.copernicus.content
Version: 3.8
Summary: Custom Content-Types for Land Copernicus
Home-page: http://github.com/eea/land.copernicus.content
Author: European Environment Agency
Author-email: webadmin@eea.europa.eu
License: GPL
Keywords: land copernicus eea content-types plone zope
Platform: UNKNOWN
Classifier: Programming Language :: Python
Requires-Dist: setuptools
Requires-Dist: archetypes.schemaextender
Requires-Dist: lxml
Requires-Dist: plone.app.registry
Requires-Dist: z3c.jbot
Requires-Dist: Wand
Requires-Dist: Products.DataGridField
Requires-Dist: collective.z3cform.datagridfield (==1.2.0)
Requires-Dist: eea.forms
Requires-Dist: Products.ATVocabularyManager
Requires-Dist: eea.cache
Requires-Dist: eea.geotags
Requires-Dist: plone.app.async
Requires-Dist: five.pt
Requires-Dist: plone.stringinterp (==1.0.14)
Requires-Dist: eea.rdfmarshaller (>=10.5)
